panda_terminal/__init__.py
panda_terminal/keyboard.py
panda_terminal/keyboard.pyi
panda_terminal/terminal.py
panda_terminal/terminal.pyi
panda_terminal-1.0.dist-info/licenses/LICENSE
panda_terminal-1.0.dist-info/METADATA
panda_terminal-1.0.dist-info/WHEEL
panda_terminal-1.0.dist-info/top_level.txt
panda_terminal-1.0.dist-info/RECORD
