Metadata-Version: 2.4
Name: panda-terminal
Version: 1.0
Summary: A lightweight library for terminal games and TUI applications.
Author-email: Colin Politi <urboycolinthepanda@gmail.com>
License: MIT License
Project-URL: Homepage, https://github.com/ColinThePanda/PandaTerminal
Project-URL: Bug_Tracker, https://github.com/ColinThePanda/PandaTerminal/issues
Classifier: Programming Language :: Python :: 3
Classifier: License :: OSI Approved :: MIT License
Classifier: Operating System :: OS Independent
Requires-Python: >=3.9
License-File: LICENSE
Requires-Dist: panda-math
Dynamic: license-file
